ravens/__init__.py
ravens/dataset.py
ravens/demos.py
ravens/plot.py
ravens/test.py
ravens/train.py
ravens/agents/__init__.py
ravens/agents/conv_mlp.py
ravens/agents/dummy.py
ravens/agents/form2fit.py
ravens/agents/gt_state.py
ravens/agents/gt_state_2_step.py
ravens/agents/transporter.py
ravens/agents/transporter_6dof.py
ravens/environments/__init__.py
ravens/environments/environment.py
ravens/environments/environment_test.py
ravens/models/__init__.py
ravens/models/attention.py
ravens/models/conv_mlp.py
ravens/models/gt_state.py
ravens/models/matching.py
ravens/models/mdn_utils.py
ravens/models/regression.py
ravens/models/resnet.py
ravens/models/transport.py
ravens/models/transport_6dof.py
ravens/models/transport_ablation.py
ravens/models/transport_goal.py
ravens/tasks/__init__.py
ravens/tasks/align_box_corner.py
ravens/tasks/assembling_kits.py
ravens/tasks/block_insertion.py
ravens/tasks/cameras.py
ravens/tasks/grippers.py
ravens/tasks/manipulating_rope.py
ravens/tasks/packing_boxes.py
ravens/tasks/palletizing_boxes.py
ravens/tasks/place_red_in_green.py
ravens/tasks/primitives.py
ravens/tasks/stack_block_pyramid.py
ravens/tasks/sweeping_piles.py
ravens/tasks/task.py
ravens/tasks/towers_of_hanoi.py
ravens/utils/__init__.py
ravens/utils/pybullet_utils.py
ravens/utils/utils.py
ravens-0.1.dist-info/LICENSE
ravens-0.1.dist-info/METADATA
ravens-0.1.dist-info/WHEEL
ravens-0.1.dist-info/top_level.txt
ravens-0.1.dist-info/RECORD
