Metadata-Version: 2.1
Name: ravens
Version: 0.1
Summary: Ravens is a collection of simulated tasks in PyBullet for learning vision-based robotic manipulation.
Home-page: https://github.com/google-research/ravens
Author: Andy Zeng, Pete Florence, Daniel Seita, Jonathan Tompson, Ayzaan Wahid
Author-email: ravens-team@google.com
License: UNKNOWN
Platform: UNKNOWN
Requires-Dist: absl-py (>=0.7.0)
Requires-Dist: gym (>=0.17.3)
Requires-Dist: numpy (>=1.18.5)
Requires-Dist: pybullet (>=3.0.4)
Requires-Dist: matplotlib (>=3.1.1)
Requires-Dist: opencv-python (>=4.1.2.30)
Requires-Dist: meshcat (>=0.0.18)
Requires-Dist: scipy (>=1.4.1)
Requires-Dist: scikit-image (>=0.17.2)
Requires-Dist: tensorflow (>=2.3.0)
Requires-Dist: tensorflow-addons (>=0.11.2)
Requires-Dist: tensorflow-hub (>=0.9.0)
Requires-Dist: transforms3d (>=0.3.1)
